{
  "chart_id": "bubble_004",
  "title": "Bubble Chart (2004)",
  "dpi": 100,
  "fig_size": [
    8,
    8
  ],
  "font_size": 10,
  "palette": [
    "#1f77b4",
    "#ff7f0e",
    "#2ca02c",
    "#d62728",
    "#9467bd",
    "#8c564b",
    "#e377c2",
    "#7f7f7f",
    "#bcbd22",
    "#17becf"
  ],
  "marker": "o",
  "sample_size": 8,
  "point_size_range": [
    30,
    100
  ],
  "x_ticks": [
    -12000.0,
    -4500.0,
    3000.0,
    10500.0,
    18000.0
  ],
  "y_ticks": [
    66.0,
    68.5,
    71.0,
    73.5,
    76.0
  ],
  "x_ticks_encrypted": [
    -12000.0,
    -8250.0,
    -4500.0,
    -750.0,
    3000.0,
    6750.0,
    10500.0,
    14250.0,
    18000.0
  ],
  "y_ticks_encrypted": [
    66.0,
    67.25,
    68.5,
    69.75,
    71.0,
    72.25,
    73.5,
    74.75,
    76.0
  ],
  "series_color": {
    "NGA": [
      "#9467bd"
    ],
    "USA": [
      "#ff7f0e"
    ],
    "ZAF": [
      "#8c564b"
    ],
    "IND": [
      "#17becf"
    ],
    "FRA": [
      "#1f77b4"
    ],
    "BRA": [
      "#7f7f7f"
    ],
    "IDN": [
      "#e377c2"
    ],
    "TUR": [
      "#d62728"
    ]
  },
  "label_position": "outside",
  "random_seed": 42,
  "bubble_sizes": {
    "T1": 56.1,
    "T2": 140.14,
    "T3": 103.23,
    "T4": 168.98,
    "T5": 86.44,
    "T6": 78.22,
    "T7": 6.29,
    "T8": 16.45
  }
}